dockship/__init__.py
dockship/__main__.py
dockship/utils.py
dockship-0.1.4.dist-info/DESCRIPTION.rst
dockship-0.1.4.dist-info/METADATA
dockship-0.1.4.dist-info/RECORD
dockship-0.1.4.dist-info/WHEEL
dockship-0.1.4.dist-info/entry_points.txt
dockship-0.1.4.dist-info/metadata.json
dockship-0.1.4.dist-info/top_level.txt
