Metadata-Version: 2.0
Name: dockship
Version: 0.1.4
Summary: Run AI models in Docker containers
Home-page: https://github.com/dockship/dockship
Author: Unreal AI Technologies Pvt. Ltd.
Author-email: deepak@unrealai.xyz
License: UNKNOWN
Platform: UNKNOWN
Classifier: License :: OSI Approved :: MIT License
Classifier: Programming Language :: Python :: 3
Classifier: Programming Language :: Python :: 3.6
Classifier: Operating System :: OS Independent
Requires-Dist: alive-progress
Requires-Dist: fire
Requires-Dist: requests
Requires-Dist: tqdm
